setup.cfg
setup.py
feedzilla_api.egg-info/PKG-INFO
feedzilla_api.egg-info/SOURCES.txt
feedzilla_api.egg-info/dependency_links.txt
feedzilla_api.egg-info/not-zip-safe
feedzilla_api.egg-info/requires.txt
feedzilla_api.egg-info/top_level.txt
pyfeed/__init__.py
pyfeed/constants.py
pyfeed/pyfeed.py
pyfeed/pyfeedClass.py
pyfeed/test.py
pyfeed/utilities.py