Metadata-Version: 1.1
Name: feedzilla-api
Version: 0.3
Summary: Unofficial Feedzilla Python API Wrapper
Home-page: https://github.com/melvin0008/PyFeed
Author: Melvin Philips
Author-email: me@melvinphilips.com
License: UNKNOWN
Download-URL: https://github.com/melvin0008/PyFeed/tarball/0.3
Keywords: feedzilla-api,api,feedzilla,feedzilla-wrapper
Platform: UNKNOWN
